{"cameraMode":{"drawMode":0,"name":"Shaded","section":"Shading Mode"},"sceneLighting":true,"audioPlay":false,"sceneViewState":{"m_AlwaysRefresh":false,"showFog":true,"showSkybox":false,"showFlares":true,"showImageEffects":true,"showParticleSystems":true,"showVisualEffectGraphs":true,"m_FxEnabled":true},"in2DMode":false,"pivot":{"x":-6.826872825622559,"y":78.72874450683594,"z":-150.6563262939453},"rotation":{"x":-0.47234755754470827,"y":-0.09806438535451889,"z":0.053086500614881518,"w":-0.8743999004364014},"size":2.876190662384033,"orthographic":false}