{"cameraMode":{"drawMode":0,"name":"Shaded","section":"Shading Mode"},"sceneLighting":true,"audioPlay":false,"sceneViewState":{"m_AlwaysRefresh":false,"showFog":true,"showSkybox":true,"showFlares":true,"showImageEffects":true,"showParticleSystems":true,"showVisualEffectGraphs":true,"m_FxEnabled":true},"in2DMode":false,"pivot":{"x":880.5970458984375,"y":622.7545166015625,"z":-1023.9669799804688},"rotation":{"x":0.025833457708358766,"y":0.0038431771099567415,"z":0.0005201884778216481,"w":0.9997043013572693},"size":10.0,"orthographic":false}